LICENSE
README.md
setup.py
merge_tokenizers/__init__.py
merge_tokenizers/types.py
merge_tokenizers/version.py
merge_tokenizers.egg-info/PKG-INFO
merge_tokenizers.egg-info/SOURCES.txt
merge_tokenizers.egg-info/dependency_links.txt
merge_tokenizers.egg-info/not-zip-safe
merge_tokenizers.egg-info/requires.txt
merge_tokenizers.egg-info/top_level.txt
merge_tokenizers/aligners/__init__.py
merge_tokenizers/aligners/base.py
merge_tokenizers/aligners/dtw.py
merge_tokenizers/aligners/dtw_py.py
merge_tokenizers/aligners/fast_dtw.py
merge_tokenizers/aligners/greedy_coverage.py
merge_tokenizers/aligners/greedy_coverage_py.py
merge_tokenizers/aligners/greedy_distance.py
merge_tokenizers/aligners/tamuhey.py
merge_tokenizers/aligners/word_ids.py
merge_tokenizers/aligners/dtw_c/dtw.c
merge_tokenizers/aligners/greedy_coverage_c/greedy_coverage.c
merge_tokenizers/utils/__init__.py
merge_tokenizers/utils/distances.py
merge_tokenizers/utils/heuristics.py
merge_tokenizers/utils/preprocess.py