Metadata-Version: 2.1
Name: merge-tokenizers
Version: 0.0.6
Summary: Package to merge tokens from different tokenizers.
Author: Symanto Research GmbH
Author-email: jose.gonzalez@symanto.com
Classifier: Development Status :: 4 - Beta
Classifier: Environment :: Console
Classifier: Intended Audience :: Developers
Classifier: Topic :: Scientific/Engineering :: Artificial Intelligence
Classifier: License :: Other/Proprietary License
Classifier: Programming Language :: Python :: 3 :: Only
Classifier: Operating System :: MacOS :: MacOS X
Classifier: Operating System :: Microsoft :: Windows
Classifier: Operating System :: POSIX
Requires-Python: >=3.8.0
License-File: LICENSE
Requires-Dist: levenshtein
Requires-Dist: pydantic
Requires-Dist: spacy-alignments
Requires-Dist: scikit-learn
Requires-Dist: fastdtw
Requires-Dist: ukkonen
Requires-Dist: numba
Provides-Extra: dev
Requires-Dist: black; extra == "dev"
Requires-Dist: flake8; extra == "dev"
Requires-Dist: mypy; extra == "dev"
Requires-Dist: types-requests; extra == "dev"
Requires-Dist: pytest; extra == "dev"
Requires-Dist: isort; extra == "dev"
Requires-Dist: autoflake; extra == "dev"
Requires-Dist: pre-commit; extra == "dev"
